simpleBDB/__init__.py
simpleBDB/db.py
simpleBDB-1.1.30.dist-info/LICENSE
simpleBDB-1.1.30.dist-info/METADATA
simpleBDB-1.1.30.dist-info/WHEEL
simpleBDB-1.1.30.dist-info/top_level.txt
simpleBDB-1.1.30.dist-info/RECORD
