Metadata-Version: 2.1
Name: simpleBDB
Version: 1.1.30
Summary: A simple wrapper for bsddb3
Home-page: https://github.com/deltarod/simpleBDB/
Author: Tristan Miller
Author-email: Tristan.Miller@nau.edu
License: UNKNOWN
Platform: UNKNOWN
Classifier: Programming Language :: Python :: 3.6
Classifier: License :: OSI Approved :: GNU Lesser General Public License v3 (LGPLv3)
Requires-Python: >=3.6
License-File: LICENSE
Requires-Dist: berkeleydb
Requires-Dist: pandas (>=1.1.4)
Requires-Dist: decorator
Provides-Extra: test
Requires-Dist: pytest ; extra == 'test'
